Metadata-Version: 2.1
Name: tvdsb-student-api
Version: 1.7
Summary: A Python library and CLI tool for interacting with the TVDSB Student Portal service 
Home-page: https://github.com/Ewpratten/tvdsb-student-api
Author: Evan Pratten
Author-email: ewpratten@retrylife.ca
License: GPLv3
Platform: UNKNOWN
